salt_cellar/__init__.py
salt_cellar/exceptions.py
salt_cellar/lvdatatype.py
salt_cellar/salt_cellar.py
salt_cellar-0.1.1.dist-info/LICENSE
salt_cellar-0.1.1.dist-info/METADATA
salt_cellar-0.1.1.dist-info/WHEEL
salt_cellar-0.1.1.dist-info/top_level.txt
salt_cellar-0.1.1.dist-info/RECORD
