Metadata-Version: 2.1
Name: salt-cellar
Version: 0.1.1
Summary: A tool for retreiving and unpacking stored ELS data.
Home-page: https://bitbucket.org/saao/salt_cellar
Author: SALT Software Engineers
Author-email: salt-support@salt.ac.za
License: MIT license
Platform: UNKNOWN
Classifier: License :: OSI Approved :: MIT License
Classifier: Operating System :: OS Independent
Classifier: Intended Audience :: Developers
Classifier: Natural Language :: English
Classifier: Programming Language :: Python :: 3
Requires-Python: >=3.6
Requires-Dist: pymysql
Requires-Dist: sqlalchemy
